serpentkit/__init__.py
serpentkit/pinyin.py
serpentkit/py.typed
serpentkit/response.py
serpentkit/result.py
serpentkit/vali/__init__.py
serpentkit/vali/processor_func.py
serpentkit/vali/vali_proc.py
serpentkit/vali/validator_func.py
serpentkit-0.0.1.dist-info/METADATA
serpentkit-0.0.1.dist-info/WHEEL
serpentkit-0.0.1.dist-info/RECORD
