Metadata-Version: 2.4
Name: serpentkit
Version: 0.0.1
Summary: Add your description here
Author-email: FlyQRCode <2314910401@qq.com>
Requires-Python: >=3.10
Requires-Dist: pypinyin>=0.54.0
Requires-Dist: vierror>=0.0.2
